cookit/__init__.py
cookit/common/__init__.py
cookit/common/debug.py
cookit/common/maths.py
cookit/common/other.py
cookit/common/signal.py
cookit/common/text.py
cookit/common/data/__init__.py
cookit/common/data/base.py
cookit/common/data/cache.py
cookit/common/data/deco_collector.py
cookit/common/data/pagination.py
cookit/common/deprecated/__init__.py
cookit/common/deprecated/data.py
cookit/common/deprecated/nullcontext.py
cookit/common/deprecated/sized_list.py
cookit/jinja/__init__.py
cookit/jinja/common.py
cookit/jinja/filters.py
cookit/loguru/__init__.py
cookit/loguru/common.py
cookit/nonebot/__init__.py
cookit/nonebot/alconna/__init__.py
cookit/nonebot/alconna/common.py
cookit/nonebot/alconna/receipt.py
cookit/nonebot/base/__init__.py
cookit/nonebot/base/dependency.py
cookit/nonebot/base/plugin.py
cookit/nonebot/base/tools.py
cookit/nonebot/localstore/__init__.py
cookit/nonebot/localstore/base.py
cookit/pw/__init__.py
cookit/pw/router.py
cookit/pw/screenshot.py
cookit/pw/jinja/__init__.py
cookit/pw/jinja/base.py
cookit/pw/loguru/__init__.py
cookit/pw/loguru/router.py
cookit/pyd/__init__.py
cookit/pyd/compat.py
cookit/pyd/deprecated.py
cookit/pyd/util.py
cookit-0.13.2.dist-info/METADATA
cookit-0.13.2.dist-info/WHEEL
cookit-0.13.2.dist-info/licenses/LICENSE
cookit-0.13.2.dist-info/RECORD
