Metadata-Version: 2.4
Name: cookit
Version: 0.13.2
Summary: A toolkit for self use.
Project-URL: homepage, https://github.com/lgc2333/cookit
Author-email: LgCookie <lgc2333@126.com>
License: MIT
License-File: LICENSE
Requires-Python: <4.0,>=3.10
Requires-Dist: typing-extensions>=4.14.1
Provides-Extra: all
Requires-Dist: anyio>=4.8.0; extra == 'all'
Requires-Dist: fleep>=1.0.1; extra == 'all'
Requires-Dist: jinja2>=3.1.5; extra == 'all'
Requires-Dist: loguru>=0.7.3; extra == 'all'
Requires-Dist: nonebot-plugin-alconna>=0.54.2; extra == 'all'
Requires-Dist: nonebot-plugin-localstore>=0.7.4; extra == 'all'
Requires-Dist: nonebot2>=2.4.1; extra == 'all'
Requires-Dist: playwright>=1.50.0; extra == 'all'
Requires-Dist: pydantic!=2.5.0,!=2.5.1,<3.0.0,>=1.10.0; extra == 'all'
Requires-Dist: yarl>=1.18.3; extra == 'all'
Provides-Extra: common
Requires-Dist: fleep>=1.0.1; extra == 'common'
Provides-Extra: jinja
Requires-Dist: jinja2>=3.1.5; extra == 'jinja'
Provides-Extra: loguru
Requires-Dist: loguru>=0.7.3; extra == 'loguru'
Provides-Extra: nonebot
Requires-Dist: nonebot-plugin-alconna>=0.54.2; extra == 'nonebot'
Requires-Dist: nonebot-plugin-localstore>=0.7.4; extra == 'nonebot'
Requires-Dist: nonebot2>=2.4.1; extra == 'nonebot'
Provides-Extra: nonebot-alconna
Requires-Dist: nonebot-plugin-alconna>=0.54.2; extra == 'nonebot-alconna'
Requires-Dist: nonebot2>=2.4.1; extra == 'nonebot-alconna'
Provides-Extra: nonebot-base
Requires-Dist: nonebot2>=2.4.1; extra == 'nonebot-base'
Provides-Extra: nonebot-localstore
Requires-Dist: nonebot-plugin-localstore>=0.7.4; extra == 'nonebot-localstore'
Requires-Dist: nonebot2>=2.4.1; extra == 'nonebot-localstore'
Provides-Extra: playwright
Requires-Dist: anyio>=4.8.0; extra == 'playwright'
Requires-Dist: playwright>=1.50.0; extra == 'playwright'
Requires-Dist: yarl>=1.18.3; extra == 'playwright'
Provides-Extra: pw
Requires-Dist: anyio>=4.8.0; extra == 'pw'
Requires-Dist: playwright>=1.50.0; extra == 'pw'
Requires-Dist: yarl>=1.18.3; extra == 'pw'
Provides-Extra: pyd
Requires-Dist: pydantic!=2.5.0,!=2.5.1,<3.0.0,>=1.10.0; extra == 'pyd'
Provides-Extra: pydantic
Requires-Dist: pydantic!=2.5.0,!=2.5.1,<3.0.0,>=1.10.0; extra == 'pydantic'
